yggdrasil_client/__init__.py
yggdrasil_client/exceptions.py
yggdrasil_client-0.1.0.dev10.dist-info/LICENSE
yggdrasil_client-0.1.0.dev10.dist-info/METADATA
yggdrasil_client-0.1.0.dev10.dist-info/WHEEL
yggdrasil_client-0.1.0.dev10.dist-info/RECORD
