Metadata-Version: 2.1
Name: yggdrasil-client
Version: 0.1.0.dev10
Summary: Minecraft Yggdrasil protocol compatible client based on ADOFAI. Supports mojang backend.
Home-page: https://github.com/Silverteal/yggdrasil-client
License: MIT
Keywords: minecraft,mc,authlib,authlib-injector,client,mojang,api,yggdrasil
Author: Silverteal
Author-email: 67404722+Silverteal@users.noreply.github.com
Requires-Python: >=3.12,<4.0
Classifier: License :: OSI Approved :: MIT License
Classifier: Programming Language :: Python :: 3
Classifier: Programming Language :: Python :: 3.12
Requires-Dist: adofai (>=0.1.0.dev6,<0.2.0)
Requires-Dist: aiohttp[speedups] (>=3.10.8,<4.0.0)
Project-URL: Repository, https://github.com/Silverteal/yggdrasil-client
